mapc_dcf/__init__.py
mapc_dcf/channel.py
mapc_dcf/constants.py
mapc_dcf/dcf.py
mapc_dcf/logger.py
mapc_dcf/nodes.py
mapc_dcf/utils.py
mapc_dcf-0.2.5.dist-info/licenses/LICENSE
mapc_dcf-0.2.5.dist-info/METADATA
mapc_dcf-0.2.5.dist-info/WHEEL
mapc_dcf-0.2.5.dist-info/top_level.txt
mapc_dcf-0.2.5.dist-info/RECORD
