Metadata-Version: 2.4
Name: mapc_dcf
Version: 0.2.5
Summary: IEEE 802.11 DCF Simulator
Author-email: Maksymilian Wojnar <maksymilian.wojnar@agh.edu.pl>, Wojciech Ciężobka <wojciech.ciezobka@agh.edu.pl>, Katarzyna Kosek-Szott <katarzyna.kosek-szott@agh.edu.pl>, Krzysztof Rusek <krzysztof.rusek@agh.edu.pl>, Szymon Szott <szymon.szott@agh.edu.pl>
License: Creative Commons Legal Code
Keywords: 802.11,distributed coordination function,simulator
Requires-Python: >=3.12
License-File: LICENSE
Requires-Dist: chex~=0.1.91
Requires-Dist: intervaltree~=3.1.0
Requires-Dist: jax~=0.8.0
Requires-Dist: pandas~=2.3.3
Requires-Dist: simpy~=4.1.1
Requires-Dist: tfp-nightly
Dynamic: license-file
